{"config":{"output_file":null,"full_docs":false,"pub_only":true,"reachable_only":true,"distro_crate":false,"signatures":false,"borrow_data":false},"version":"0.19.1","compilation":{"directory":"/home/pavel/.cargo/registry/src/github.com-1ecc6299db9ec823/memory_units-0.4.0","program":"/home/pavel/.rustup/toolchains/stable-x86_64-unknown-linux-gnu/bin/rls","arguments":["--crate-name","memory_units","/home/pavel/.cargo/registry/src/github.com-1ecc6299db9ec823/memory_units-0.4.0/src/lib.rs","--json=diagnostic-rendered-ansi","--crate-type","lib","--emit=dep-info,metadata","-C","embed-bitcode=no","-C","debuginfo=2","-C","metadata=8bfe333c6f7b7962","-C","extra-filename=-8bfe333c6f7b7962","--out-dir","/home/pavel/Near/create-near-NFTapp/NFT-project/contract/target/rls/debug/deps","-L","dependency=/home/pavel/Near/create-near-NFTapp/NFT-project/contract/target/rls/debug/deps","--cap-lints","allow","--error-format=json","--sysroot","/home/pavel/.rustup/toolchains/stable-x86_64-unknown-linux-gnu"],"output":"/home/pavel/Near/create-near-NFTapp/NFT-project/contract/target/rls/debug/deps/libmemory_units-8bfe333c6f7b7962.rmeta"},"prelude":{"crate_id":{"name":"memory_units","disambiguator":[14874583898096877034,0]},"crate_root":"/home/pavel/.cargo/registry/src/github.com-1ecc6299db9ec823/memory_units-0.4.0/src","external_crates":[{"file_name":"/home/pavel/.cargo/registry/src/github.com-1ecc6299db9ec823/memory_units-0.4.0/src/lib.rs","num":1,"id":{"name":"core","disambiguator":[2034785968469428135,0]}},{"file_name":"/home/pavel/.cargo/registry/src/github.com-1ecc6299db9ec823/memory_units-0.4.0/src/lib.rs","num":2,"id":{"name":"compiler_builtins","disambiguator":[12655493918929861395,0]}},{"file_name":"/home/pavel/.cargo/registry/src/github.com-1ecc6299db9ec823/memory_units-0.4.0/src/lib.rs","num":3,"id":{"name":"rustc_std_workspace_core","disambiguator":[13424910470399079611,0]}}],"span":{"file_name":"/home/pavel/.cargo/registry/src/github.com-1ecc6299db9ec823/memory_units-0.4.0/src/lib.rs","byte_start":0,"byte_end":4958,"line_start":1,"line_end":215,"column_start":1,"column_end":19}},"imports":[{"kind":"GlobUse","ref_id":null,"span":{"file_name":"/home/pavel/.cargo/registry/src/github.com-1ecc6299db9ec823/memory_units-0.4.0/src/lib.rs","byte_start":4956,"byte_end":4957,"line_start":215,"line_end":215,"column_start":17,"column_end":18},"alias_span":null,"name":"*","value":"","parent":{"krate":0,"index":0}}],"defs":[{"kind":"Mod","id":{"krate":0,"index":0},"span":{"file_name":"/home/pavel/.cargo/registry/src/github.com-1ecc6299db9ec823/memory_units-0.4.0/src/lib.rs","byte_start":0,"byte_end":4958,"line_start":1,"line_end":215,"column_start":1,"column_end":19},"name":"","qualname":"::","value":"/home/pavel/.cargo/registry/src/github.com-1ecc6299db9ec823/memory_units-0.4.0/src/lib.rs","parent":null,"children":[{"krate":0,"index":1},{"krate":0,"index":2},{"krate":0,"index":3},{"krate":0,"index":4},{"krate":0,"index":7},{"krate":0,"index":10},{"krate":0,"index":11},{"krate":0,"index":12},{"krate":0,"index":13},{"krate":0,"index":14},{"krate":0,"index":15},{"krate":0,"index":17},{"krate":0,"index":20},{"krate":0,"index":21},{"krate":0,"index":37},{"krate":0,"index":40},{"krate":0,"index":42},{"krate":0,"index":44},{"krate":0,"index":45},{"krate":0,"index":46},{"krate":0,"index":49},{"krate":0,"index":50},{"krate":0,"index":52},{"krate":0,"index":54},{"krate":0,"index":56},{"krate":0,"index":58},{"krate":0,"index":61},{"krate":0,"index":65},{"krate":0,"index":69},{"krate":0,"index":73},{"krate":0,"index":23},{"krate":0,"index":28},{"krate":0,"index":36}],"decl_id":null,"docs":" Crate for safe conversion between units of memory.\n","sig":null,"attributes":[{"value":"/ Crate for safe conversion between units of memory.","span":{"file_name":"/home/pavel/.cargo/registry/src/github.com-1ecc6299db9ec823/memory_units-0.4.0/src/lib.rs","byte_start":0,"byte_end":54,"line_start":1,"line_end":1,"column_start":1,"column_end":55}},{"value":"deny(missing_docs)","span":{"file_name":"/home/pavel/.cargo/registry/src/github.com-1ecc6299db9ec823/memory_units-0.4.0/src/lib.rs","byte_start":56,"byte_end":78,"line_start":3,"line_end":3,"column_start":1,"column_end":23}},{"value":"no_std","span":{"file_name":"/home/pavel/.cargo/registry/src/github.com-1ecc6299db9ec823/memory_units-0.4.0/src/lib.rs","byte_start":79,"byte_end":89,"line_start":4,"line_end":4,"column_start":1,"column_end":11}}]},{"kind":"Function","id":{"krate":0,"index":15},"span":{"file_name":"/home/pavel/.cargo/registry/src/github.com-1ecc6299db9ec823/memory_units-0.4.0/src/lib.rs","byte_start":2597,"byte_end":2604,"line_start":118,"line_end":118,"column_start":8,"column_end":15},"name":"size_of","qualname":"::size_of","value":"pub fn size_of<T>() -> Bytes","parent":null,"children":[],"decl_id":null,"docs":" Returns the size of a type in [`Bytes`].","sig":null,"attributes":[{"value":"/ Returns the size of a type in [`Bytes`].","span":{"file_name":"/home/pavel/.cargo/registry/src/github.com-1ecc6299db9ec823/memory_units-0.4.0/src/lib.rs","byte_start":2303,"byte_end":2347,"line_start":101,"line_end":101,"column_start":1,"column_end":45}},{"value":"/","span":{"file_name":"/home/pavel/.cargo/registry/src/github.com-1ecc6299db9ec823/memory_units-0.4.0/src/lib.rs","byte_start":2348,"byte_end":2351,"line_start":102,"line_end":102,"column_start":1,"column_end":4}},{"value":"/ # Example","span":{"file_name":"/home/pavel/.cargo/registry/src/github.com-1ecc6299db9ec823/memory_units-0.4.0/src/lib.rs","byte_start":2352,"byte_end":2365,"line_start":103,"line_end":103,"column_start":1,"column_end":14}},{"value":"/","span":{"file_name":"/home/pavel/.cargo/registry/src/github.com-1ecc6299db9ec823/memory_units-0.4.0/src/lib.rs","byte_start":2366,"byte_end":2369,"line_start":104,"line_end":104,"column_start":1,"column_end":4}},{"value":"/ ```rust","span":{"file_name":"/home/pavel/.cargo/registry/src/github.com-1ecc6299db9ec823/memory_units-0.4.0/src/lib.rs","byte_start":2370,"byte_end":2381,"line_start":105,"line_end":105,"column_start":1,"column_end":12}},{"value":"/ # use memory_units::*;","span":{"file_name":"/home/pavel/.cargo/registry/src/github.com-1ecc6299db9ec823/memory_units-0.4.0/src/lib.rs","byte_start":2382,"byte_end":2408,"line_start":106,"line_end":106,"column_start":1,"column_end":27}},{"value":"/ #[repr(C)]","span":{"file_name":"/home/pavel/.cargo/registry/src/github.com-1ecc6299db9ec823/memory_units-0.4.0/src/lib.rs","byte_start":2409,"byte_end":2423,"line_start":107,"line_end":107,"column_start":1,"column_end":15}},{"value":"/ struct Hello {","span":{"file_name":"/home/pavel/.cargo/registry/src/github.com-1ecc6299db9ec823/memory_units-0.4.0/src/lib.rs","byte_start":2424,"byte_end":2442,"line_start":108,"line_end":108,"column_start":1,"column_end":19}},{"value":"/     a: u32,","span":{"file_name":"/home/pavel/.cargo/registry/src/github.com-1ecc6299db9ec823/memory_units-0.4.0/src/lib.rs","byte_start":2443,"byte_end":2458,"line_start":109,"line_end":109,"column_start":1,"column_end":16}},{"value":"/     b: u32,","span":{"file_name":"/home/pavel/.cargo/registry/src/github.com-1ecc6299db9ec823/memory_units-0.4.0/src/lib.rs","byte_start":2459,"byte_end":2474,"line_start":110,"line_end":110,"column_start":1,"column_end":16}},{"value":"/ }","span":{"file_name":"/home/pavel/.cargo/registry/src/github.com-1ecc6299db9ec823/memory_units-0.4.0/src/lib.rs","byte_start":2475,"byte_end":2480,"line_start":111,"line_end":111,"column_start":1,"column_end":6}},{"value":"/","span":{"file_name":"/home/pavel/.cargo/registry/src/github.com-1ecc6299db9ec823/memory_units-0.4.0/src/lib.rs","byte_start":2481,"byte_end":2484,"line_start":112,"line_end":112,"column_start":1,"column_end":4}},{"value":"/ assert_eq!(size_of::<Hello>(), Bytes(4 + 4));","span":{"file_name":"/home/pavel/.cargo/registry/src/github.com-1ecc6299db9ec823/memory_units-0.4.0/src/lib.rs","byte_start":2485,"byte_end":2534,"line_start":113,"line_end":113,"column_start":1,"column_end":50}},{"value":"/ ```","span":{"file_name":"/home/pavel/.cargo/registry/src/github.com-1ecc6299db9ec823/memory_units-0.4.0/src/lib.rs","byte_start":2535,"byte_end":2542,"line_start":114,"line_end":114,"column_start":1,"column_end":8}},{"value":"/","span":{"file_name":"/home/pavel/.cargo/registry/src/github.com-1ecc6299db9ec823/memory_units-0.4.0/src/lib.rs","byte_start":2543,"byte_end":2546,"line_start":115,"line_end":115,"column_start":1,"column_end":4}},{"value":"/ [`Bytes`]: struct.Bytes.html","span":{"file_name":"/home/pavel/.cargo/registry/src/github.com-1ecc6299db9ec823/memory_units-0.4.0/src/lib.rs","byte_start":2547,"byte_end":2579,"line_start":116,"line_end":116,"column_start":1,"column_end":33}},{"value":"inline","span":{"file_name":"/home/pavel/.cargo/registry/src/github.com-1ecc6299db9ec823/memory_units-0.4.0/src/lib.rs","byte_start":2580,"byte_end":2589,"line_start":117,"line_end":117,"column_start":1,"column_end":10}}]},{"kind":"Trait","id":{"krate":0,"index":17},"span":{"file_name":"/home/pavel/.cargo/registry/src/github.com-1ecc6299db9ec823/memory_units-0.4.0/src/lib.rs","byte_start":3073,"byte_end":3082,"line_start":136,"line_end":136,"column_start":11,"column_end":20},"name":"RoundUpTo","qualname":"::RoundUpTo","value":"RoundUpTo<T>","parent":null,"children":[{"krate":0,"index":19}],"decl_id":null,"docs":" A trait defining round up conversion between various memory units.","sig":null,"attributes":[{"value":"/ A trait defining round up conversion between various memory units.","span":{"file_name":"/home/pavel/.cargo/registry/src/github.com-1ecc6299db9ec823/memory_units-0.4.0/src/lib.rs","byte_start":2655,"byte_end":2725,"line_start":122,"line_end":122,"column_start":1,"column_end":71}},{"value":"/","span":{"file_name":"/home/pavel/.cargo/registry/src/github.com-1ecc6299db9ec823/memory_units-0.4.0/src/lib.rs","byte_start":2726,"byte_end":2729,"line_start":123,"line_end":123,"column_start":1,"column_end":4}},{"value":"/ # Example","span":{"file_name":"/home/pavel/.cargo/registry/src/github.com-1ecc6299db9ec823/memory_units-0.4.0/src/lib.rs","byte_start":2730,"byte_end":2743,"line_start":124,"line_end":124,"column_start":1,"column_end":14}},{"value":"/","span":{"file_name":"/home/pavel/.cargo/registry/src/github.com-1ecc6299db9ec823/memory_units-0.4.0/src/lib.rs","byte_start":2744,"byte_end":2747,"line_start":125,"line_end":125,"column_start":1,"column_end":4}},{"value":"/ ```rust","span":{"file_name":"/home/pavel/.cargo/registry/src/github.com-1ecc6299db9ec823/memory_units-0.4.0/src/lib.rs","byte_start":2748,"byte_end":2759,"line_start":126,"line_end":126,"column_start":1,"column_end":12}},{"value":"/ # use memory_units::*;","span":{"file_name":"/home/pavel/.cargo/registry/src/github.com-1ecc6299db9ec823/memory_units-0.4.0/src/lib.rs","byte_start":2760,"byte_end":2786,"line_start":127,"line_end":127,"column_start":1,"column_end":27}},{"value":"/ // `bytes` contains the size of 1 memory page in bytes.","span":{"file_name":"/home/pavel/.cargo/registry/src/github.com-1ecc6299db9ec823/memory_units-0.4.0/src/lib.rs","byte_start":2787,"byte_end":2846,"line_start":128,"line_end":128,"column_start":1,"column_end":60}},{"value":"/ let mut bytes: Bytes = Pages(1).into();","span":{"file_name":"/home/pavel/.cargo/registry/src/github.com-1ecc6299db9ec823/memory_units-0.4.0/src/lib.rs","byte_start":2847,"byte_end":2890,"line_start":129,"line_end":129,"column_start":1,"column_end":44}},{"value":"/","span":{"file_name":"/home/pavel/.cargo/registry/src/github.com-1ecc6299db9ec823/memory_units-0.4.0/src/lib.rs","byte_start":2891,"byte_end":2894,"line_start":130,"line_end":130,"column_start":1,"column_end":4}},{"value":"/ // Adding 1 to `bytes` makes it larger than the single page.","span":{"file_name":"/home/pavel/.cargo/registry/src/github.com-1ecc6299db9ec823/memory_units-0.4.0/src/lib.rs","byte_start":2895,"byte_end":2959,"line_start":131,"line_end":131,"column_start":1,"column_end":65}},{"value":"/ bytes.0 += 1;","span":{"file_name":"/home/pavel/.cargo/registry/src/github.com-1ecc6299db9ec823/memory_units-0.4.0/src/lib.rs","byte_start":2960,"byte_end":2977,"line_start":132,"line_end":132,"column_start":1,"column_end":18}},{"value":"/ let pages: Pages = bytes.round_up_to();","span":{"file_name":"/home/pavel/.cargo/registry/src/github.com-1ecc6299db9ec823/memory_units-0.4.0/src/lib.rs","byte_start":2978,"byte_end":3021,"line_start":133,"line_end":133,"column_start":1,"column_end":44}},{"value":"/ assert_eq!(pages, Pages(2));","span":{"file_name":"/home/pavel/.cargo/registry/src/github.com-1ecc6299db9ec823/memory_units-0.4.0/src/lib.rs","byte_start":3022,"byte_end":3054,"line_start":134,"line_end":134,"column_start":1,"column_end":33}},{"value":"/ ```","span":{"file_name":"/home/pavel/.cargo/registry/src/github.com-1ecc6299db9ec823/memory_units-0.4.0/src/lib.rs","byte_start":3055,"byte_end":3062,"line_start":135,"line_end":135,"column_start":1,"column_end":8}}]},{"kind":"Method","id":{"krate":0,"index":19},"span":{"file_name":"/home/pavel/.cargo/registry/src/github.com-1ecc6299db9ec823/memory_units-0.4.0/src/lib.rs","byte_start":3176,"byte_end":3187,"line_start":138,"line_end":138,"column_start":8,"column_end":19},"name":"round_up_to","qualname":"::RoundUpTo::round_up_to","value":"pub fn round_up_to(Self) -> T","parent":{"krate":0,"index":17},"children":[],"decl_id":null,"docs":" Returns minimum number of `T` to fit amount of space occupied by `self`.\n","sig":null,"attributes":[{"value":"/ Returns minimum number of `T` to fit amount of space occupied by `self`.","span":{"file_name":"/home/pavel/.cargo/registry/src/github.com-1ecc6299db9ec823/memory_units-0.4.0/src/lib.rs","byte_start":3092,"byte_end":3168,"line_start":137,"line_end":137,"column_start":5,"column_end":81}}]},{"kind":"Trait","id":{"krate":0,"index":21},"span":{"file_name":"/home/pavel/.cargo/registry/src/github.com-1ecc6299db9ec823/memory_units-0.4.0/src/lib.rs","byte_start":3528,"byte_end":3536,"line_start":154,"line_end":154,"column_start":11,"column_end":19},"name":"ByteSize","qualname":"::ByteSize","value":"ByteSize","parent":null,"children":[{"krate":0,"index":22}],"decl_id":null,"docs":" A trait defining the size, in bytes, of one unit of `Self`.","sig":null,"attributes":[{"value":"/ A trait defining the size, in bytes, of one unit of `Self`.","span":{"file_name":"/home/pavel/.cargo/registry/src/github.com-1ecc6299db9ec823/memory_units-0.4.0/src/lib.rs","byte_start":3311,"byte_end":3374,"line_start":146,"line_end":146,"column_start":1,"column_end":64}},{"value":"/","span":{"file_name":"/home/pavel/.cargo/registry/src/github.com-1ecc6299db9ec823/memory_units-0.4.0/src/lib.rs","byte_start":3375,"byte_end":3378,"line_start":147,"line_end":147,"column_start":1,"column_end":4}},{"value":"/ # Example","span":{"file_name":"/home/pavel/.cargo/registry/src/github.com-1ecc6299db9ec823/memory_units-0.4.0/src/lib.rs","byte_start":3379,"byte_end":3392,"line_start":148,"line_end":148,"column_start":1,"column_end":14}},{"value":"/","span":{"file_name":"/home/pavel/.cargo/registry/src/github.com-1ecc6299db9ec823/memory_units-0.4.0/src/lib.rs","byte_start":3393,"byte_end":3396,"line_start":149,"line_end":149,"column_start":1,"column_end":4}},{"value":"/ ```rust","span":{"file_name":"/home/pavel/.cargo/registry/src/github.com-1ecc6299db9ec823/memory_units-0.4.0/src/lib.rs","byte_start":3397,"byte_end":3408,"line_start":150,"line_end":150,"column_start":1,"column_end":12}},{"value":"/ # use memory_units::*;","span":{"file_name":"/home/pavel/.cargo/registry/src/github.com-1ecc6299db9ec823/memory_units-0.4.0/src/lib.rs","byte_start":3409,"byte_end":3435,"line_start":151,"line_end":151,"column_start":1,"column_end":27}},{"value":"/ println!(\"The size of one word in bytes is {}.\", Words::BYTE_SIZE.0);","span":{"file_name":"/home/pavel/.cargo/registry/src/github.com-1ecc6299db9ec823/memory_units-0.4.0/src/lib.rs","byte_start":3436,"byte_end":3509,"line_start":152,"line_end":152,"column_start":1,"column_end":74}},{"value":"/ ```","span":{"file_name":"/home/pavel/.cargo/registry/src/github.com-1ecc6299db9ec823/memory_units-0.4.0/src/lib.rs","byte_start":3510,"byte_end":3517,"line_start":153,"line_end":153,"column_start":1,"column_end":8}}]},{"kind":"Const","id":{"krate":0,"index":22},"span":{"file_name":"/home/pavel/.cargo/registry/src/github.com-1ecc6299db9ec823/memory_units-0.4.0/src/lib.rs","byte_start":3605,"byte_end":3614,"line_start":156,"line_end":156,"column_start":11,"column_end":20},"name":"BYTE_SIZE","qualname":"::ByteSize::BYTE_SIZE","value":"Bytes","parent":{"krate":0,"index":21},"children":[],"decl_id":null,"docs":" The size, in bytes, of a single unit of `Self`.\n","sig":null,"attributes":[{"value":"/ The size, in bytes, of a single unit of `Self`.","span":{"file_name":"/home/pavel/.cargo/registry/src/github.com-1ecc6299db9ec823/memory_units-0.4.0/src/lib.rs","byte_start":3543,"byte_end":3594,"line_start":155,"line_end":155,"column_start":5,"column_end":56}}]},{"kind":"Struct","id":{"krate":0,"index":37},"span":{"file_name":"/home/pavel/.cargo/registry/src/github.com-1ecc6299db9ec823/memory_units-0.4.0/src/lib.rs","byte_start":3763,"byte_end":3768,"line_start":163,"line_end":163,"column_start":13,"column_end":18},"name":"Bytes","qualname":"::Bytes","value":"","parent":null,"children":[],"decl_id":null,"docs":" Memory size specified in bytes.\n","sig":null,"attributes":[]},{"kind":"Mod","id":{"krate":0,"index":23},"span":{"file_name":"/home/pavel/.cargo/registry/src/github.com-1ecc6299db9ec823/memory_units-0.4.0/src/lib.rs","byte_start":3834,"byte_end":3840,"line_start":168,"line_end":168,"column_start":9,"column_end":15},"name":"wasm32","qualname":"::wasm32","value":"/home/pavel/.cargo/registry/src/github.com-1ecc6299db9ec823/memory_units-0.4.0/src/lib.rs","parent":null,"children":[{"krate":0,"index":24},{"krate":0,"index":25},{"krate":0,"index":77},{"krate":0,"index":80},{"krate":0,"index":82},{"krate":0,"index":84},{"krate":0,"index":85},{"krate":0,"index":86},{"krate":0,"index":89},{"krate":0,"index":90},{"krate":0,"index":92},{"krate":0,"index":94},{"krate":0,"index":96},{"krate":0,"index":98},{"krate":0,"index":100},{"krate":0,"index":103},{"krate":0,"index":107},{"krate":0,"index":111},{"krate":0,"index":115},{"krate":0,"index":119},{"krate":0,"index":122},{"krate":0,"index":124},{"krate":0,"index":126},{"krate":0,"index":127},{"krate":0,"index":128},{"krate":0,"index":131},{"krate":0,"index":132},{"krate":0,"index":134},{"krate":0,"index":136},{"krate":0,"index":138},{"krate":0,"index":140},{"krate":0,"index":142},{"krate":0,"index":145},{"krate":0,"index":149},{"krate":0,"index":153},{"krate":0,"index":157}],"decl_id":null,"docs":" WebAssembly-specific sizes and units.\n","sig":null,"attributes":[{"value":"/ WebAssembly-specific sizes and units.","span":{"file_name":"/home/pavel/.cargo/registry/src/github.com-1ecc6299db9ec823/memory_units-0.4.0/src/lib.rs","byte_start":3847,"byte_end":3888,"line_start":169,"line_end":169,"column_start":5,"column_end":46}}]},{"kind":"Struct","id":{"krate":0,"index":77},"span":{"file_name":"/home/pavel/.cargo/registry/src/github.com-1ecc6299db9ec823/memory_units-0.4.0/src/lib.rs","byte_start":4016,"byte_end":4021,"line_start":176,"line_end":176,"column_start":17,"column_end":22},"name":"Words","qualname":"::wasm32::Words","value":"","parent":null,"children":[],"decl_id":null,"docs":" Memory size specified in `wasm32` words.\n","sig":null,"attributes":[]},{"kind":"Struct","id":{"krate":0,"index":119},"span":{"file_name":"/home/pavel/.cargo/registry/src/github.com-1ecc6299db9ec823/memory_units-0.4.0/src/lib.rs","byte_start":4248,"byte_end":4253,"line_start":183,"line_end":183,"column_start":17,"column_end":22},"name":"Pages","qualname":"::wasm32::Pages","value":"","parent":null,"children":[],"decl_id":null,"docs":" Memory size specified in WebAssembly [memory pages][memory page].","sig":null,"attributes":[]},{"kind":"Mod","id":{"krate":0,"index":28},"span":{"file_name":"/home/pavel/.cargo/registry/src/github.com-1ecc6299db9ec823/memory_units-0.4.0/src/lib.rs","byte_start":4460,"byte_end":4466,"line_start":195,"line_end":195,"column_start":9,"column_end":15},"name":"target","qualname":"::target","value":"/home/pavel/.cargo/registry/src/github.com-1ecc6299db9ec823/memory_units-0.4.0/src/lib.rs","parent":null,"children":[{"krate":0,"index":29},{"krate":0,"index":30},{"krate":0,"index":33},{"krate":0,"index":161},{"krate":0,"index":164},{"krate":0,"index":166},{"krate":0,"index":168},{"krate":0,"index":169},{"krate":0,"index":170},{"krate":0,"index":173},{"krate":0,"index":174},{"krate":0,"index":176},{"krate":0,"index":178},{"krate":0,"index":180},{"krate":0,"index":182},{"krate":0,"index":184},{"krate":0,"index":187},{"krate":0,"index":191},{"krate":0,"index":195},{"krate":0,"index":199},{"krate":0,"index":203},{"krate":0,"index":206},{"krate":0,"index":208},{"krate":0,"index":210},{"krate":0,"index":211},{"krate":0,"index":212},{"krate":0,"index":215},{"krate":0,"index":216},{"krate":0,"index":218},{"krate":0,"index":220},{"krate":0,"index":222},{"krate":0,"index":224},{"krate":0,"index":226},{"krate":0,"index":229},{"krate":0,"index":233},{"krate":0,"index":237},{"krate":0,"index":241}],"decl_id":null,"docs":" Sizes and units for the current compilation target.\n","sig":null,"attributes":[{"value":"cfg(not(target_arch = \"wasm32\"))","span":{"file_name":"/home/pavel/.cargo/registry/src/github.com-1ecc6299db9ec823/memory_units-0.4.0/src/lib.rs","byte_start":4416,"byte_end":4451,"line_start":194,"line_end":194,"column_start":1,"column_end":36}},{"value":"/ Sizes and units for the current compilation target.","span":{"file_name":"/home/pavel/.cargo/registry/src/github.com-1ecc6299db9ec823/memory_units-0.4.0/src/lib.rs","byte_start":4473,"byte_end":4528,"line_start":196,"line_end":196,"column_start":5,"column_end":60}}]},{"kind":"Struct","id":{"krate":0,"index":161},"span":{"file_name":"/home/pavel/.cargo/registry/src/github.com-1ecc6299db9ec823/memory_units-0.4.0/src/lib.rs","byte_start":4666,"byte_end":4671,"line_start":204,"line_end":204,"column_start":17,"column_end":22},"name":"Words","qualname":"::target::Words","value":"","parent":null,"children":[],"decl_id":null,"docs":" Memory size specified in words.\n","sig":null,"attributes":[]},{"kind":"Struct","id":{"krate":0,"index":203},"span":{"file_name":"/home/pavel/.cargo/registry/src/github.com-1ecc6299db9ec823/memory_units-0.4.0/src/lib.rs","byte_start":4908,"byte_end":4913,"line_start":211,"line_end":211,"column_start":17,"column_end":22},"name":"Pages","qualname":"::target::Pages","value":"","parent":null,"children":[],"decl_id":null,"docs":" Memory size specified in [memory pages][memory page].","sig":null,"attributes":[]}],"impls":[],"refs":[],"macro_refs":[],"relations":[]}